altdss_schema/__about__.py
altdss_schema/__init__.py
altdss_schema/altdss_models.py
altdss_schema/pydantic_complex.py
nrel_altdss_schema-0.0.2.dist-info/METADATA
nrel_altdss_schema-0.0.2.dist-info/WHEEL
nrel_altdss_schema-0.0.2.dist-info/licenses/LICENSE
nrel_altdss_schema-0.0.2.dist-info/RECORD
